CONTRIBUTING.rst
DodgeCaravan-2016-CDR.txt
LICENSE.rst
MANIFEST.in
README.rst
requirements.txt
setup.py
pyvit/__init__.py
pyvit/bus.py
pyvit/can.py
pyvit/dispatch.py
pyvit/log.py
pyvit.egg-info/PKG-INFO
pyvit.egg-info/SOURCES.txt
pyvit.egg-info/dependency_links.txt
pyvit.egg-info/requires.txt
pyvit.egg-info/top_level.txt
pyvit/file/__init__.py
pyvit/file/db/__init__.py
pyvit/file/db/jsondb.py
pyvit/file/log/__init__.py
pyvit/file/log/candump.py
pyvit/hw/__init__.py
pyvit/hw/cantact.py
pyvit/hw/logplayer.py
pyvit/hw/loopback.py
pyvit/hw/peak.py
pyvit/hw/socketcan.py
pyvit/proto/__init__.py
pyvit/proto/isotp.py
pyvit/proto/obdii.py
pyvit/proto/uds.py
pyvit/utils/__init__.py
pyvit/utils/queue.py
test/__init__.py
test/can_test.py
test/dispatch_test.py
test/file_candump_test.py
test/isotp_test.py
test/json_db_test.py
test/log_test.py
test/loopback_test.py
test/uds_test.py