Metadata-Version: 1.1
Name: pyvit
Version: 0.2.0
Summary: Python Vehicle Inteface Toolkit
Home-page: http://github.com/linklayer/pyvit
Author: Eric Evenchick
Author-email: eric@evenchick.com
License: GPLv3
Platform: UNKNOWN
Classifier: Development Status :: 3 - Alpha
Classifier: License :: OSI Approved :: GNU General Public License v3 (GPLv3)
Classifier: Topic :: Software Development :: Libraries
Classifier: Topic :: Software Development :: Embedded Systems
